aftpy/__init__.py
aftpy/aftmap.py
aftpy/aftmaps.py
aftpy/cmdtools.py
aftpy/getaftdata.py
aftpy/utilities.py
aftpy/visulalization.py
aftpy-2.0.2.dist-info/LICENSE
aftpy-2.0.2.dist-info/METADATA
aftpy-2.0.2.dist-info/WHEEL
aftpy-2.0.2.dist-info/entry_points.txt
aftpy-2.0.2.dist-info/top_level.txt
aftpy-2.0.2.dist-info/RECORD
