Metadata-Version: 2.1
Name: aftpy
Version: 2.0.2
Summary: Python package to Read, Visualize and download AFTmap data.
Author-email: Bibhuti Kumar Jha <bibhuraushan1@gmail.com>
License: MIT
Project-URL: Homepage, https://bibhuraushan.github.io/aftpy
Project-URL: Repository, https://github.com/me/spam.git
Keywords: Sun,Dataloader,AFT,SFT
Classifier: License :: OSI Approved :: MIT License
Classifier: Programming Language :: Python
Requires-Python: >=3.8
License-File: LICENSE
Requires-Dist: matplotlib
Requires-Dist: numpy
Requires-Dist: astropy
Requires-Dist: h5py
Requires-Dist: sunpy
Requires-Dist: pandas
